README.txt
bootstrap.py
buildout.cfg
fabfile.py
setup.py
conf/base.cfg
conf/database.cfg
conf/deploy-snip.cfg
conf/develop.cfg
conf/develop_theme.cfg
conf/get_data
conf/haproxy.cfg
conf/ldap.cfg
conf/production.cfg
conf/sources.cfg
conf/staging.cfg
conf/versions.cfg
conf/xdv.cfg
docs/CONTRIBUTORS.txt
docs/HISTORY.txt
docs/LICENSE.GPL
docs/LICENSE.txt
docs/UPGRADE.txt
docs/plone.org-setup/account-database.txt
docs/plone.org-setup/statistics.txt
docs/plone.org-setup/subversion-setup.txt
scripts/catalog_rebuild.py
scripts/clear_catalog.py
scripts/findDuplicatePSCFiles.py
scripts/get_user_properties.py
scripts/html_validity.py
scripts/mirror.py
scripts/reindexPloneNet.py
scripts/reindex_products.py
scripts/removePloneNetInstanceSchema.py
scripts/restrictPoiTrackers.py
scripts/updateMostSchemata.py
scripts/update_comments.py
scripts/update_package_download_counts.py
src/Products/__init__.py
src/Products.PloneOrg.egg-info/PKG-INFO
src/Products.PloneOrg.egg-info/SOURCES.txt
src/Products.PloneOrg.egg-info/dependency_links.txt
src/Products.PloneOrg.egg-info/namespace_packages.txt
src/Products.PloneOrg.egg-info/not-zip-safe
src/Products.PloneOrg.egg-info/requires.txt
src/Products.PloneOrg.egg-info/top_level.txt
src/Products/PloneOrg/__init__.py
src/Products/PloneOrg/caching.py
src/Products/PloneOrg/configure.zcml
src/Products/PloneOrg/overrides.zcml
src/Products/PloneOrg/purger.py
src/Products/PloneOrg/setuphandlers.py
src/Products/PloneOrg/team.txt
src/Products/PloneOrg/testing.py
src/Products/PloneOrg/tests.py
src/Products/PloneOrg/upgrade.py
src/Products/PloneOrg/userschema.py
src/Products/PloneOrg/Extensions/html_validity.py
src/Products/PloneOrg/browser/__init__.py
src/Products/PloneOrg/browser/configure.zcml
src/Products/PloneOrg/browser/group.py
src/Products/PloneOrg/browser/interfaces.py
src/Products/PloneOrg/browser/overrides.zcml
src/Products/PloneOrg/browser/recaptcha_widget.pt
src/Products/PloneOrg/browser/recaptcha_widget.py
src/Products/PloneOrg/browser/register.py
src/Products/PloneOrg/profiles/default/actions.xml
src/Products/PloneOrg/profiles/default/controlpanel.xml
src/Products/PloneOrg/profiles/default/cssregistry.xml
src/Products/PloneOrg/profiles/default/deployment-various.txt
src/Products/PloneOrg/profiles/default/jsregistry.xml
