Metadata-Version: 1.0
Name: Products.PloneOrg
Version: 1.4
Summary: Plone.org site policy package.
Home-page: http://svn.plone.org/svn/plone/Products.PloneOrg
Author: Plone Foundation
Author-email: plone-developers@lists.sourceforge.net
License: GPL
Platform: UNKNOWN
Classifier: Framework :: Plone
Classifier: Programming Language :: Python
Classifier: Topic :: Software Development :: Libraries :: Python Modules
